UM22006UNO/__init__.py
UM22006UNO/biseccion.py
UM22006UNO/cramer.py
UM22006UNO/ejemplos.py
UM22006UNO/gauss.py
UM22006UNO/gauss_jordan.py
UM22006UNO/gauss_seidel.py
UM22006UNO/jacobi.py
UM22006UNO/lu.py
UM22006UNO/metodos.py
um22006uno-0.1.dist-info/licenses/LICENSE
um22006uno-0.1.dist-info/METADATA
um22006uno-0.1.dist-info/WHEEL
um22006uno-0.1.dist-info/top_level.txt
um22006uno-0.1.dist-info/RECORD
